py3_http_utils/__init__.py
py3_http_utils/response/__init__.py
py3_http_utils/response/httpx.py
py3_http_utils/response/requests.py
py3_http_utils-1.0.0.dist-info/licenses/LICENSE
py3_http_utils-1.0.0.dist-info/METADATA
py3_http_utils-1.0.0.dist-info/WHEEL
py3_http_utils-1.0.0.dist-info/top_level.txt
py3_http_utils-1.0.0.dist-info/RECORD
