Metadata-Version: 2.4
Name: py3-http-utils
Version: 1.0.0
Summary: The Python3 Http Utils Developed By Guolei
Home-page: https://github.com/guolei19850528/py3_http_utils
Author: guolei
Author-email: 174000902@qq.com
License: MIT
Requires-Python: >=3.0
License-File: LICENSE
Requires-Dist: addict
Requires-Dist: retrying
Requires-Dist: jsonschema
Requires-Dist: setuptools
Requires-Dist: wheel
Dynamic: author
Dynamic: author-email
Dynamic: description
Dynamic: description-content-type
Dynamic: home-page
Dynamic: license
Dynamic: license-file
Dynamic: requires-dist
Dynamic: requires-python
Dynamic: summary
